<author type="socialmedia" lang="es" gender="xx" age_group="xx" url="">
	<documents count="18">
		<document id="bb62c0cedee84886eaf7e5d253d7d31" url=""><![CDATA[para ti ...<br/><br/>Me contaron de Romeo y Julieta 
<br />y pense ke hermoso cuento 
<br />y ahora resulta 
<br />ke es mas grande 
<br />ke es mas bello 
<br />esto, esto que por ti yo siento. 
<br /><br />Cruzare los montes, 
<br />los rios, los valles 
<br />por irte a encontrar 
<br />salvaria tormentas, ciclones, dragones 
<br />sin exajerar 
<br />por poder mirarme en tus ojos bonitos 
<br />y vivir la gloria de estar a tu lado 
<br />porke en mi ya siento ke t necesito 
<br />ke me he enamorado 
<br />por poder mirarme en tus ojos bonitos 
<br />y vivir la gloria d estar a tu lado 
<br />porke en mi ya siento que te necesito 
<br />eso y mas hare. 
<br /><br />Por asegurar la sonrisa de tu alma 
<br />buscando equidad 
<br />yo podria empeñar lo mas caro 
<br />que tengo ke es mi libertad 
<br />y seria un honor hay amor ser tu esclavo 
<br />seria tu juguete por mi voluntad 
<br />y si un dia glorioso en tus brazos acabo 
<br />que felicidad 
<br />si seria un honor hay amor ser tu esclavo 
<br />seria tu juguete por mi voluntad 
<br />y si un dia glorioso en tus brazos acabo 
<br />ke felicidad.
]]>
		</document>
		<document id="8b45712a8fc14972a8f279b445f2704" url=""><![CDATA[buena letra<br/><br/>Hey, espera un momento y escuchame bien. 
<br />Vas en busca de paz, y que tal si en mi puedas hayar, ese poco de amor. 
<br />Que inhunde tu alma y cautive tu mundo. 
<br />Y convierta en segundos tu dolor, en cancion 
<br />Ven, yo se que no es facil volver a confiar. 
<br />Que no deja un buen sabor todo ese engaño. 
<br />Y no voy a hacerte daño. 
<br />Aun no es tarde debes darte una oportunidad. 
<br /><br />Y quiero ser yo quien sorprenda tu sueño. 
<br />Trayendo mi canto con la madrugada. 
<br />Es mucho pedir si quiero ser tu dueño. 
<br />Y ser la razon de todas tus miradas. 
<br />Mis ojos podrian decirlo por mi. 
<br /><br />Yo quiero adornar tu camino con rosas. 
<br />Que donde tu vayas perfumen tus pasos. 
<br />Te quiero mostrar que la vida es hermosa. 
<br />Que puedo partir tu tristeza en pedasos. 
<br />Podria morir por tenerte en mis brazos. 
<br /><br />Hey, yo no quiero ser uno mas del monton. 
<br />No esque vaya a millon, hace siglos que espero tu amor. 
<br />Ya no pude aguantar, desde que te vi te he querido en silencio. 
<br />Y se rompe mi pecho, de verdad dejate amar. 
<br /><br />Hey, quiero ser el angel que cuide de ti. 
<br />Yo solo quiero ser luz, para tu alma. 
<br />Tu sonrisa en la mañana. 
<br />Estoy seguro que tambien podras amarme asi.. 
<br /><br />Y quiero ser yo quien sorprenda tu sueño. 
<br />Trayendo mi canto con la madrugada. 
<br />Es mucho pedir si quiero ser tu dueño. 
<br />Y ser la razon de todas tus miradas. 
<br />Yo podria vestirme de color cada dia en el que no haya sol. 
<br />Yo podria hacer feliz tu vida solo con cantarte mi cancion 
<br /><br />Yo quiero adornar tu camino con rosas. 
<br />Que donde tu vayas perfumen tus pasos. 
<br />Te quiero mostrar que la vida es hermosa. 
<br />Que puedo partir tu tristeza en pedasos. 
<br />Mis ojos podrian decirlo por mi.
]]>
		</document>
		<document id="ed38dea85fb093ab2f351eb07c67abd" url=""><![CDATA[gran ofertoon!!<br/><br/>OFERTA!! 
<br /><br />Gran oferta un corazón rojo lleno de defectos y virtudes, dispuesto a dejar de latir por su dueña… Lo único que pide es que lo quieran un poquito y confíen en él... Aguanta todo. Es Recargable, Resistente. , Duradero..., Tierno y Fiel, Decídete ya!!!!!
<br />Aprovecha esta oportunidad...,
<br />¡¡¡¡¡Es una ganga ¡! (Aprobado por la asociación de corazones querendones y luchadores....)
<br />Incluye un cuerpo con 206 huesos, pocas neuronas y muchas hormonas
<br />Forrado de piel genuina, (de sangre azul)
<br />Incluye el cuerpo que Contiene 2 piernas, 2 brazos, 2 oídos, 1 nariz, 1 boca mordible (ehhhhh)...
<br /><br />Para este producto se aceptan cheques en blanco, Tarjetas de crédito, O bien pagos diarios de mil ocho mil besos y ¡¡¡ apapachos, pagos con cuerpo matico hasta nuevo aviso ( se aplican restricciones).
<br /><br />Nota: El abuso de este producto puede producir inundaciones lagrimales.
<br /><br />Instructivo:
<br />Para su mejor uso siga las siguientes instrucciones:
<br /><br />1. Trátelo con cariño.
<br />2. Recargüelo diariamente con una dosis de amor.
<br />3. Utilice las piernas cuando lleguen los violadores de papantla (Campeón en 200mts.)
<br />4. Utilice los brazos cuando halla que pagar las cuentas.
<br />5. Utilice los oídos cuando quiera que le escuchen todos sus panchos y cursilerías.
<br />6. Utilice la boca cuando quiera disfrutar del producto.
<br /><br />Advertencias:
<br />1. No se deje al alcance de las niñas mayores de 16 años.
<br />2. Si se deja a altas temperaturas se puede sobrecalentar.
<br />3. El mal uso de este producto puede ocasionar traslado de dominio.
<br />4. El exceso de mariscos provoca mayor rendimiento.
<br />5. Contiene detector de mentiras.
<br />6. Incluye quemador (es decir todo mundo sabrá de tu producto)
<br /><br />Ventajas:
<br />1. Adaptabilidad a todo tipo de terreno.
<br />2. Hecho de material moldeable.
<br />3. Esta a disposición las 24 hrs. (contiene amigo localizador e identificador de llamadas)
<br />4. Capacidad para soportar hasta 3 panchos al día.
<br />5. Compatibilidad con unidad de cajero automático.
<br />6. Contiene manos ergonómicas.
<br /><br />Desventajas:
<br />1. Único en su ramo y en el mercado.
<br />2. Solo es apto para niñas bonitas.
<br />3. Poca memoria ram.
<br />4. No incluye escáner humano. (es decir no es mirón)
<br />5. No incluye skins (es decir no es doble cara).
<br /><br />Fecha de caducidad: huuy¡?..Hasta que el cuerpo aguante
<br /><br />Nota:
<br />En caso de fallas o sugerencias para mejorar el producto, llamar a las oficinas o bien escribir a: (La dirección que sea)
]]>
		</document>
		<document id="9791b34ef834d37fb38b332822ef8ede" url=""><![CDATA[kIce hAcertE fEliz..... C m 0lviDo kE y0 tMb kEriA sErLo<br/><br/>mALdiTa  eStupiDez!!
<br /><br />Sabes bien 
<br />que te di lo que soy 
<br />Y tu amor 
<br />es limosna y dolor 
<br />Yo de ti 
<br />fui un amante sin amor 
<br />Se acabo 
<br />no me pidas perdón 
<br /><br />Mírate, 
<br />estas sola otra vez 
<br />Y mírame, 
<br />que mi culpa no es 
<br />Deja de 
<br />atormentarme al corazón 
<br />Lárgate 
<br />que ya no te quiero ver 
<br /><br />No hay nadie en este mundo que me hiciera tanto daño 
<br />Fui tonto no lo niego me llegaste a convencer 
<br />Y vienes y me mientes mientras vamos de la mano 
<br />Seguro estas pensando que me tienes a tus pies 
<br /><br />Maldita estupidez 
<br /><br />Yo quise hacerte feliz 
<br />Pero el problema es que no quieres 
<br />ser feliz 
<br />Se me olvido a mi también 
<br />que yo también quería serlo 
<br />Y lo lamento no vuelvo a caer 
<br />No diré 
<br />que no habrá nadie mejor que yo 
<br />Si los hay, 
<br />Pero es que dudo que alguien crea en ti como yo 
<br />Como te pude aguantar 
<br /><br />Hoy diré 
<br />que me arrepentí 
<br />De vivir el tiempo junto a ti 
<br />Tal vez yo 
<br />solo te imagine 
<br />La verdad es que yo nunca te mire 
<br /><br />Ojala aprendas a distinguir 
<br />Entre el amor, 
<br />el ego, el odio y la pasión 
<br />Te olvide 
<br />solo por que te odie 
<br />Solo fue 
<br />una pinche obsesión 
<br /><br />Lo peor de todo es que sabes perfecto que eres mala 
<br />Y andas presumiéndole a la gente que eres fiel 
<br />No digas que me extrañas porque no te creo nada 
<br />Yo se que tu actitud es tu mas grande estupidez 
<br /><br />Maldita estupidez 
<br /><br />Yo quise hacerte feliz 
<br />Pero el problemas es que no quieres 
<br />ser feliz 
<br />Se me olvido, 
<br />se me olvido a mi también 
<br />que yo también quería serlo 
<br />Y lo lamento no vuelvo a caer 
<br />No diré 
<br />que no habrá nadie mejor que yo 
<br />Si los hay, 
<br />Pero es que dudo que alguien crea en ti como yo 
<br />Como te pude aguantar 
<br /><br />Yo quise hacerte feliz 
<br />Pero el problema es que no quieres 
<br />ser feliz 
<br />Se me olvido, 
<br />se me olvido a mi también 
<br />que yo también quería serlo 
<br />Y lo prometo no vuelvo a caer 
<br />No diré 
<br />que no habrá nadie mejor que yo 
<br />si los hay, 
<br />Pero es que dudo que alguien vea en ti lo que tu 
<br />Nunca me pudiste dar 
<br /><br />Y se me olvidaba… 
<br />Te detesto tanto
<br /><br />ps aki les dejo esto nunka pense ke llegaria a dedicar algo asi
<br /><br />pero  literalmente ...alguien me obligo....
<br /><br />ahora espero mejor ya olvidar todo para 
<br /><br />no hacerme mas daño     = (
]]>
		</document>
		<document id="527ac07bc2eed6df24ae6accc83576ae" url=""><![CDATA[miedo<br/><br/>Un profundo miedo agobia hoy mi alma,
<br />un miedo estremecedor, incalculable
<br />incomprensible, inexplicable, 
<br />un miedo pavoroso, penetrante.
<br /><br />Miedo de sentir, miedo de soñar,
<br />miedo de amar, miedo de perder,
<br />miedo de aburrir, miedo de cambiar,
<br />miedo de aprender, miedo de crecer. 
<br />Miedo que me impide llorar
<br />incluso cuando mi alma esta a punto de estallar.
<br /><br />Es un miedo tan intenso
<br />que ni siquiera me deja amar. 
<br />Como quisiera volver a ser aquel que fui,
<br />caminar sin preocupaciones por la vida,
<br />volver a mis raíces, volver a sentir
<br />volver a soñar, e incluso a vivir. 
<br />Pero este miedo interminable, que me apresa,
<br />me condena a esa prisión sin rejas,
<br />a ese dolor ambiguo, intolerable
<br />que se apodero de mi, en aquel instante. 
<br />Dejándome sin fuerzas, sin ánimos.
<br />arrebatándome mis sueños, mis esperanzas,
<br />despojándome de lo único añoraba
<br />las ansias de vivir, como yo esperaba.
]]>
		</document>
		<document id="3a3840352a01290b7a870a31fbaef21b" url=""><![CDATA[La VidA eS....<br/><br/>La Vida es Oportunidad: Aprovéchala 
<br /><br />La Vida es Belleza: Admírala 
<br /><br />La Vida es Beatitud: Saboréala 
<br /><br />La Vida es un Sueño: Hazla Realidad 
<br /><br />La vida es un Reto: Afróntalo 
<br /><br />La Vida es un Deber: Cúmplelo 
<br /><br />La Vida es un Juego: Juégalo 
<br /><br />La Vida es un Himno: Cántalo 
<br /><br />La Vida es Preciosa: Cuídala 
<br /><br />La Vida es Riqueza: Consérvala 
<br /><br />La Vida es Amor: Gózalo 
<br /><br />La Vida es un Misterio: Devélalo 
<br /><br />La Vida es Promesa: Cúmplela 
<br /><br />La Vida es Tristeza: Supérala 
<br /><br />La Vida es un Combate: Acéptalo 
<br /><br />La Vida es Felicidad: Merécela 
<br /><br />La Vida es... Vida: !Defiéndela
]]>
		</document>
		<document id="49824f4f7b05b098379c6b150bb23d0f" url=""><![CDATA[nO me pIdAs<br/><br/>No me pidas que te QUIERA...Ya lo hice sin que me lo  pidieras. 
<br /><br />No me pidas que te odie...Odiaría que lo intentaras. 
<br /><br />No me pidas ser amigos..Ya lo fuimos,¿lo olvidaste? 
<br /><br />No me pidas mis temores..Te los di y los despejaste. 
<br /><br />No me pidas que volemos. Ya lo hicimos.. y ME SOLTASTE!!. 
<br /><br />No me pidas mis sueños.... Sabes de sobra que vives en ellos. 
<br /><br />No me pidas mis miedos....Conseguiste vencerlos. 
<br /><br />No me pidas el olvido..... Porque no puedo conseguir olvidarte 
<br /><br />No me pidas mi rencor... sabes de sobra que no lo tengo 
<br /><br />No me pidas tristeza... Tú fuiste mi motivo de alegría. 
<br /><br />No me pidas perdón.... Sabes que no hacen falta palabras  de  disculpa 
<br /><br />No me pidas el cielo...Lo rompimos, ¿no es cierto? 
<br /><br />No me pidas que me vaya.... Siempre estaré contigo a pesar de la distancia.. 
<br /><br />No me pidas mi vergüenza... Yo contigo de eso no gasto. 
<br /><br />No me pidas mis suspiros..Sabes que todos son para ti. 
<br /><br />No me pidas que te ayude..Lo hago a cada instante. 
<br /><br />No me pidas tiempo.......Eso ya te lo estoy dando. 
<br /><br />No me pidas sueños...........Podrías rompérmelos. 
<br /><br />No me pidas lágrimas......Ya las derramé por ti
]]>
		</document>
		<document id="4925f366b3075cb99289f79ec51893d0" url=""><![CDATA[olvidarte no he podido<br/><br/>Dicen que la distancia es la causa del olvido 
<br /><br />eso lo dice solo aquel que nunca ha querido... 
<br /><br />No se que tiene mi corazón 
<br /><br />que no quiere estar con migo 
<br /><br />y le pregunto que con quien 
<br /><br />y me dice que con tigo 
<br /><br />Este corazón que late 
<br /><br />y cada día piensa en ti 
<br /><br />nunca podrás olvidarte 
<br /><br />ya que siempre estarás en mi 
<br /><br />Y aunque dicen que la ausencia 
<br /><br />causa el olvido... 
<br /><br />ausente estas en mi vida 
<br /><br />y olvidarte no he podido.
]]>
		</document>
		<document id="15c262b9fdb47078ecab2d4b2a61834d" url=""><![CDATA[sOlO sOy yO...<br/><br/>Siento que todo lo que había “logrado” no estuvo bien logrado, porque ahora me siento más solo que nunca, quiero sentirme especial para alguien, quiero saber que alguien me quiere, y que sin mi, le costaría vivir… 
<br /><br />No puedo seguir así, en soledad… todo gira, todos ríen, pero ¡yo no soy todos!, yo lloro, mi alma y mi corazón ya no aguantan más dolor, necesito tu mano... Es como si estuviera en arenas movedizas, y que cada vez que respiro me hundo mas y mas… 
<br /><br />Quiero que alguien me ayude, que alguien me de su mano, quiero que me quieran, necesito de ti... porque todos viven así!?, felices, ya no puedo seguir así…en soledad… 
<br /><br />…porque tengo que ser diferente… porque no puedo ser como ellos, todos muy felices y con fuerzas para demostrar quienes son realmente… 
<br /><br />Lo único que anhelo es ser feliz, pero serlo con todas sus letras y tildes... pero suplicando una amistad, no voy a lograr nada; me da un poco de rabia y pena a la vez, porque yo siempre estoy dispuesto a ayudar y escuchar a la gente que lo necesite o que quiera y en ese momento me siento bien, cuando estoy escuchando, pero después me doy cuenta , que no importa cuantas veces escuche a la gente, siempre voy a seguir siendo el misma niño solitario con ganas de querer y ser querido, con ganas de que alguien me conozca de verdad... no importa… al fin y al cabo……. soy solo yo. 
<br /><br /><img class="smiley" src="http://www.pan.net/smilies/unsure.gif" alt=":)" />
]]>
		</document>
		<document id="fe47b12ec5f129f9f70382107bb2c5de" url=""><![CDATA[ayuDaMe<br/><br/>Aunque quisiera no podré olvidarte 
<br />mil veces ya lo intente 
<br />siempre fracaso y vuelvo a recordarte. 
<br /><br />Todos los días salgo a buscarte 
<br />será un milagro el encontrarte 
<br />pues no dejaste huellas al marcharte. 
<br /><br />Un cementerio es mi corazón 
<br />mi mente un manicomio de dolor 
<br />donde los sueños pierden la razón. 
<br /><br />Ayúdame, defiéndeme, 
<br />de la terrible soledad 
<br />que me deprime hasta quedar 
<br />hundido en la obscuridad. 
<br /><br />Ayúdame, hazme sentir 
<br />que donde estés piensas en mi 
<br />que la distancia te hace mal 
<br />y buscas como regresar. 
<br /><br />Ayúdame..
]]>
		</document>
		<document id="430418dba81b1b98f2657985aa915ddf" url=""><![CDATA[silOgiSmOs<br/><br/>Silogismo 1: 
<br /><br />A quién madruga Dios lo ayuda... 
<br />Quién madruga, duerme en la tarde... 
<br />Quién duerme en la tarde, no duerme en la noche... 
<br />Quién no duerme en la noche, sale de parranda!!! 
<br />Conclusión: Dios ayuda a los que sale de parranda!!! 
<br /><br />Silogismo2: 
<br /><br />Dios es amor. 
<br />El amor es ciego. 
<br />Steve Wonder es ciego. 
<br />Conclusión: Steve Wonder es Dios. 
<br /><br />Silogismo 3: 
<br /><br />Me dijeron que Yo soy nadie. 
<br />Nadie es perfecto. 
<br />Luego, yo soy perfecto. 
<br />Pero, solo Dios es perfecto. 
<br />Por lo tanto, Yo
<br />soy Dios. 
<br />Si Steve Wonder es Dios 
<br />Yo soy Steve Wonder!!! 
<br />Demonios !!! soy ciego!!! 
<br /><br />Silogismo 4: 
<br /><br />Imagínate un pedazo de queso suizo, de aquellos bien llenos 
<br />de agujeros. 
<br />Cuanto más queso, más agujeros. 
<br />Cada agujero ocupa el lugar que en el que habría queso. Así, cuanto 
<br />más agujeros, menos queso. Cuanto más queso, más agujeros y cuanto
<br />más agujeros menos queso. 
<br />Conclusión: Cuanto más queso menos queso. 
<br /><br />Silogismo 5: 
<br /><br />Cuando bebemos alcohol en exceso, terminamos borrachos.
<br />Cuando estamos borrachos, dormimos.
<br />Cuando dormimos no cometemos pecados. 
<br />Cuando no cometemos pecados, vamos al Cielo. 
<br />Conclusión: para ir al Cielo hay que ser Borracho!!! 
<br /><br />Silogismo 6: 
<br /><br />Pienso, luego
<br />existo. 
<br />Las rubias tontas no piensan, luego, las rubias tontas no existen.
<br />Mi amigo dice que no es tonto porque sale con una 
<br />rubia inteligente.
<br />Si una rubia inteligente saliese con mi amigo sería una tonta.
<br />Como las rubias tontas no existen, mi amigo no sale con nadie. 
<br />Conclusión: mi amigo es Maricón!!!. 
<br /><br />Silogismo 7: 
<br /><br />Hoy en día, los trabajadores no
<br />tienen tiempo para nada. Ahora, los vagos... tienen todo el tiempo 
<br />del mundo.
<br />El tiempo es dinero.
<br />Luego, los vagos tienen mas dinero que los trabajadores. 
<br />Conclusión: Para ser Rico, no hay que Trabajar!!! 
<br /><br />Silogismo 8
<br /><br />El beber mucho alcohol mata las neuronas, las neuronas que mata son 
<br />las más débiles.
<br />Si se mueren las débiles, quedan las más fuertes e inteligentes.
<br />Mientras más bebo alcohol, más inteligente me hago.
<br /> <img class="smiley" src="http://www.pan.net/smilies/biggrin.gif" alt=":)" />
]]>
		</document>
		<document id="2ddafac0022c8a4f8d132e848a473d7b" url=""><![CDATA[algunos versos cursis<br/><br/>Kisiera ser un lagrima tuya
<br />para nacer en tus ojos,
<br />crecer en tus mejillas
<br />y morir en tus labios.
<br /><br />Me gustaría ser la sangre
<br />ke recorre todo tu cuerpo
<br />para llegar a lo más profundo de tu corazón 
<br />y así conkistarlo desde adentro.
<br /><br />Si quererte fuera pecado....
<br />yo tendría el infierno asegurado.
<br /><br />De lejos te kiero mucho
<br />de cerca con más razón 
<br />y si un día no te veo 
<br />se me parte el corazón
<br /><br />Puede ke no seas perfecta...
<br />pero tus defectos son encantadores.
]]>
		</document>
		<document id="249dcecfc026b1aad721f3cbf2af85b3" url=""><![CDATA[mas versos....<br/><br/>Cuando me miras
<br />siento alegria y tristeza,
<br />la alegria de verte...
<br />y la tristeza de no tenerte.
<br /><br />Es verdad ke se necesita 
<br />al corazón para vivir
<br />pero más te necesito a ti 
<br />ke lo haces latir.
<br /><br />Tus ojos son dos luceros,
<br />pero tambien son dos ladrones, 
<br />el izquierdo roba suspiros..
<br />y el derecho corazones.
<br /><br />Quisiera poder olvidarte 
<br />para asi dejar de sufrir
<br />pero dejar de amarte
<br />es como dejar de vivir.
<br /><br />Mis ojos tienen la culpa
<br />y mucho van a llorar
<br />pues han visto a alguien 
<br />ke no podran olvidar.
]]>
		</document>
		<document id="676b1c6ea29050a0d197697bfd6dd2e2" url=""><![CDATA[ultimos versos del dia<br/><br/>Un imposible me mata
<br />por un imposible me muero
<br />un imposible es kerer
<br />el imposible ke kiero.
<br /><br />Que triste es el mundo 
<br />sin un ser amado
<br />pero mas triste es tenerlo
<br />y no estrar a su lado.
<br /><br />Soñe ke el sol helaba, 
<br />soñé ke el mar ardía
<br />y por soñar imposibles
<br />soñe ke me kerías.
<br /><br />Has visto como corre el agua
<br />cuando deja de llover
<br />así corren mis lagrimas 
<br />cuando te dejo de ver
<br /><br />Si dudas de mi cariño
<br />dame una puñalada
<br />y en cada gota de sangre
<br />verás tu imagen grabada.
<br /><br />Bueno se aceptan comentarios, criticas, etc etc.. espero les agraden
<br /><br /><img class="smiley" src="http://www.pan.net/smilies/mellow.gif" alt=":)" />
]]>
		</document>
		<document id="d712d94e78e3a0e65894566ecfadeca" url=""><![CDATA[para ti<br/><br/>Cuando sientas mucho frio y no sepas porque, frota tus manos y apoyalas en tu corazon...., quizas ahi encuentres la respuesta....
<br />Y en las noches cuando la luna no dibuje nada a tu favor, es ahi cuando vas a descubrir que no eres quien piensas que eres....., y si en plena mañana al abrir los ojos piensas en esa persona que quisieras tener a tu lado..., en ese y en todos los momentos de tu vida, piensa que quizas para esa persona, que para ti es un mundo, tu no lo seas..., pero siempre en algun lugar remoto del mundo lo vas a ser para alguien....
<br />Y si algun dia te arto, no es porque sea pesado, sino porque te quiero demasiado como para dejar pasar ese sentimiento, que quizas llene mi corazon de tristeza al saber que quieres a otra persona......., siempre me va a pasar lo mismo, porque por alguna razon que no pienso decirte, eres muy especial para mi, y siempre, quieras o no, vas a estar en mi corazon....te quiero.........y nunca te olvides de eso.....&quot;nunca&quot;.
<br /> <img class="smiley" src="http://www.pan.net/smilies/sad.gif" alt=":)" />
]]>
		</document>
		<document id="f3d7a7de9be8ae354e86d258df1df8f5" url=""><![CDATA[trAto<br/><br/>Trato de no pensar en tí,  
<br />de hacerme creer a mí mismo  
<br />que no me haces falta,  
<br />que no te necesito,  
<br />que puedo ser feliz sin tenerte,  
<br />que nada sin tí, es distinto. 
<br /><br />Mas no dejo ni un sólo momento  
<br />de recordarte, y desear  
<br />que estés a mi lado;  
<br />no puedo controlar  
<br />estar de tí enamorado  
<br />.  
<br />Trato de no pensar en tí,  
<br />pero sólo lo consigo  
<br />unos segundos que distraído  
<br />dedico a mentir...  
<br /><br />Clavas tus ojos en mi mirada  
<br />Hiriendo mi alma con su fuego  
<br />Exquisito y divino;  
<br />Lejos de tí, no soy el mismo;  
<br />Ojala sintieras lo que siento... 
<br /><br />Con una mano me llamas  
<br />y con la otra me alejas;  
<br />con una mirada evades mi amor  
<br />y con otra me lo acercas.
<br /><br />Sólo  puedo tenerte 
<br />aceptando que no te tengo ; 
<br />que sólo soy un juguete 
<br />que tomas cuando te apetece 
<br />y siempre olvidas luego...
]]>
		</document>
		<document id="254f4ebaa7391544c039d2d4b895d0d8" url=""><![CDATA[lejos estamos mejor<br/><br/>Hoy rompo en llanto
<br />Pues se que todo esta decidido
<br />Te quiero tanto pero no es suficiente sentirlo
<br />Hemos intentado seguir por seguir
<br />Sin reconocer que ya no hay mas por hacer
<br />Y hemos aceptado sufrir por sufrir
<br />Sin querer creer
<br /><br />querida después de romper aunque no soporte perderte es inevitable nuestra separación
<br />Y este no es momento para entender
<br />Solo hay que aceptarlo
<br />pues
<br />lejos estamos mejor
<br /><br />De aquel amor tenemos solamente el recuerdo
<br />Luna sin sol creí que se a quedado desierto
<br />En ningún momento deje de sentir de sentirte a ti
<br />Por la emoción de vivir este rompimiento se debe cumplir por que hay que seguir
<br />querida ...
<br />después de partir auque no soporte Perderte
<br />es inevitable nuestra separación
<br />Y este no es momento para entender
<br />Solo hay que aceptarlo
<br />pues
<br />lejos estamos mejor
]]>
		</document>
		<document id="85f67220e06d7f5bbab61b7c3eaab4fe" url=""><![CDATA[ACASO LO TIENES TU??<br/><br/>Busco un corazón 
<br /><br />Busco un corazón,
<br />pero no un corazón cualquiera.
<br />Tiene que ser uno compatible
<br />con la dureza de los tiempos
<br />en los que vivimos,
<br />para poder soportar las pruebas... 
<br /><br />Busco un corazón fuerte,
<br />pero lo suficientemente blando
<br />como para percibir
<br />el dolor de la gente
<br />y sensibilizarme ante ellos... 
<br /><br />Busco un corazón 
<br />con un ritmo que sea ligero
<br />pero controlado al mismo tiempo,
<br />para que me ayude a tener paciencia
<br />ante las cosas que me parecen injustas,
<br />pero que yo no puedo cambiar... 
<br /><br />Busco un corazón estable;
<br />que me dé la seguridad que necesito 
<br />para enfrentar mi destino
<br />y saber que todo tiene su lugar
<br />y su tiempo;
<br />que nada ocurre por casualidad... 
<br /><br />Busco un corazón 
<br />que simplemente ame,
<br />porque el amor 
<br />es la clave de todo:
<br />del principio y del fin,
<br />de parar o seguir,
<br />de vivir o morir... 
<br /><br />Busco un corazón especial
<br />¿¿ACASO LO TIENES TU??
]]>
		</document>
	</documents>
</author>